dp_graph/__cli__.py
dp_graph/__init__.py
dp_graph/graph.py
dp_graph/python_parser.py
dp_graph/utils.py
dp_parser-0.1.0.dist-info/licenses/LICENSE
dp_parser-0.1.0.dist-info/METADATA
dp_parser-0.1.0.dist-info/WHEEL
dp_parser-0.1.0.dist-info/entry_points.txt
dp_parser-0.1.0.dist-info/top_level.txt
dp_parser-0.1.0.dist-info/RECORD
