Metadata-Version: 2.4
Name: dp-parser
Version: 0.1.0
Summary: A package for parsing and analyzing code dependency graphs
Author: nmd2k
Classifier: Programming Language :: Python :: 3
Classifier: License :: OSI Approved :: MIT License
Classifier: Operating System :: OS Independent
Requires-Python: >=3.8
License-File: LICENSE
Requires-Dist: networkx>=3.0
Requires-Dist: astroid>=3.0
Requires-Dist: click>=8.0
Requires-Dist: tree-sitter
Requires-Dist: tree-sitter-python
Requires-Dist: tree-sitter-languages
Requires-Dist: tqdm
Provides-Extra: dev
Requires-Dist: pytest>=7.0; extra == "dev"
Requires-Dist: pytest-cov>=4.0; extra == "dev"
Requires-Dist: black>=23.0; extra == "dev"
Requires-Dist: isort>=5.0; extra == "dev"
Dynamic: license-file
